src/__init__.py
src/agents/README.md
src/agents/__init__.py
src/agents/agent_pool.py
src/cli.py
src/core/__init__.py
src/core/config.py
src/core/logging_config.py
src/core/models.py
src/core/task_manager.py
src/examples/development_cycle.py
src/llm/README.md
src/llm/chains.py
src/llm/interfaces/README.md
src/llm/interfaces/__init__.py
src/llm/interfaces/anthropic.py
src/llm/interfaces/base.py
src/llm/interfaces/openai.py
src/llm/models/README.md
src/llm/models/claude.yaml
src/llm/models/gpt.yaml
src/llm/models.py
src/llm/rate_limiter.py
src/llm/token_utils.py
src/prompts/README.md
src/prompts/base.py
src/prompts/internal/context_summarizer.yaml
src/prompts/internal/task_decomposer.yaml
src/prompts/internal/task_reminder.yaml
src/prompts/loader.py
src/prompts/schema.json
src/prompts/tasks/code_refactor.yaml
src/prompts/tasks/development_cycle.yaml
src/prompts/tasks/hello_world.yaml
src/prompts/tasks/lint_fix.yaml
src/prompts/tasks/pdf_analysis.yaml
src/prompts/types.py
src/utils/__init__.py
src/utils/storage.py
src/visualization/README.md
src/visualization/__init__.py
src/visualization/chain_visualizer.py
src/visualization/cytoscape_config.py
src/visualization/cytoscape_renderer.py
src/visualization/examples.py
src/visualization/live_visualizer.py
src/visualization/templates/live_visualization.html
src/visualization/visualize.py
llmaestro-0.1.0.dist-info/LICENSE
llmaestro-0.1.0.dist-info/METADATA
llmaestro-0.1.0.dist-info/WHEEL
llmaestro-0.1.0.dist-info/entry_points.txt
llmaestro-0.1.0.dist-info/RECORD
