Metadata-Version: 2.1
Name: llmaestro
Version: 0.1.0
Summary: A system for orchestrating LLM tasks that exceed context limits
Home-page: https://github.com/billthefighter/llmaestro
License: MIT
Keywords: llm,orchestration,ai,language-models,context-management
Author: billthefighter
Author-email: billthefighter@gmail.com
Requires-Python: >=3.11,<4.0
Classifier: License :: OSI Approved :: MIT License
Classifier: Programming Language :: Python :: 3
Classifier: Programming Language :: Python :: 3.11
Classifier: Programming Language :: Python :: 3.12
Requires-Dist: anthropic (>=0.45.2,<0.46.0)
Requires-Dist: beautifulsoup4 (>=4.12.0,<5.0.0)
Requires-Dist: click (>=8.1.0,<9.0.0)
Requires-Dist: litellm (>=1.0.0,<2.0.0)
Requires-Dist: networkx (>=3.0,<4.0)
Requires-Dist: pandas (>=2.0.0,<3.0.0)
Requires-Dist: pillow (>=11.1.0,<12.0.0)
Requires-Dist: pre-commit (>=4.1.0,<5.0.0)
Requires-Dist: py4cytoscape (>=1.5.0,<2.0.0)
Requires-Dist: pydantic (>=2.0.0,<3.0.0)
Requires-Dist: pyyaml (>=6.0.1,<7.0.0)
Requires-Dist: transformers (>=4.36.0,<5.0.0)
Requires-Dist: websockets (>=14.2,<15.0)
Project-URL: Documentation, https://github.com/billthefighter/llmaestro#readme
Project-URL: Repository, https://github.com/billthefighter/llmaestro
